PyWars/__init__.py
PyWars/_codec/__init__.py
PyWars/_codec/digest.py
PyWars/client.py
PyWars/types/__init__.py
PyWars/types/digests.py
PyWars/types/types.py
pywars-0.1.1.dist-info/LICENSE
pywars-0.1.1.dist-info/WHEEL
pywars-0.1.1.dist-info/METADATA
pywars-0.1.1.dist-info/RECORD
