Metadata-Version: 2.1
Name: pywars
Version: 0.1.1
Summary: Public topic consumer for Chat Wars API
License: MIT
Author: Jesús Enrique
Author-email: jesusefg12@gmail.com
Requires-Python: >=3.6,<4.0
Classifier: License :: OSI Approved :: MIT License
Classifier: Programming Language :: Python :: 3
Classifier: Programming Language :: Python :: 3.6
Classifier: Programming Language :: Python :: 3.7
Classifier: Programming Language :: Python :: 3.8
Classifier: Programming Language :: Python :: 3.9
Provides-Extra: dev
Requires-Dist: faust (==1.10.4)
Requires-Dist: illiterate (>=0.4,<0.5); (python_version >= "3.6" and python_version < "4.0") and (extra == "dev")
Requires-Dist: mkdocs (>=1.0.4,<2.0.0); extra == "dev"
Requires-Dist: mkdocs-material (>=4.6.0,<5.0.0); extra == "dev"
Requires-Dist: pymdown-extensions (>=8.2,<9.0); extra == "dev"
